trackingmore/__init__.py
trackingmore/test_trackingmore.py
trackingmore/trackingmore.py
trackingmore-0.2.dist-info/LICENSE
trackingmore-0.2.dist-info/METADATA
trackingmore-0.2.dist-info/WHEEL
trackingmore-0.2.dist-info/top_level.txt
trackingmore-0.2.dist-info/RECORD
