Metadata-Version: 1.0
Name: trackingmore
Version: 0.2
Summary: Python wrapper for the TrackingMore API
Home-page: https://github.com/marcoesposito1988/trackingmore-python
Author: Marco Esposito
Author-email: marcoesposito1988@gmail.com
License: LGPLv3
Platform: UNKNOWN
